pybasics/__init__.py
pybasics/biology.py
pybasics/decorators.py
pybasics/globals.py
pybasics/logs.py
pybasics/main.py
pybasics/mathelp.py
pybasics/mongodb.py
pybasics/request.py
pybasics-0.3.3.dist-info/LICENSE
pybasics-0.3.3.dist-info/METADATA
pybasics-0.3.3.dist-info/WHEEL
pybasics-0.3.3.dist-info/top_level.txt
pybasics-0.3.3.dist-info/RECORD
