Metadata-Version: 2.1
Name: pybasics
Version: 0.3.3
Summary: Basic utils in Python.
Home-page: https://github.com/synthaze/pybasics
Author: Florian Malard, PhD
Author-email: florian.malard@gmail.com
License: UNKNOWN
Project-URL: Bug Tracker, https://github.com/synthaze/pybasics/issues
Platform: UNKNOWN
Classifier: Programming Language :: Python :: 3
Classifier: License :: OSI Approved :: GNU General Public License v3 (GPLv3)
Classifier: Operating System :: OS Independent
Requires-Python: >=3.7
Requires-Dist: Pygments (==2.7.1)
Requires-Dist: pymongo (==4.0.1)
Requires-Dist: requests (==2.25.1)
Requires-Dist: urllib3 (==1.26.5)
